datapools/VERSION
datapools/__init__.py
datapools/__main__.py
datapools/api.py
datapools/cli.py
datapools/common/__init__.py
datapools/common/backend_api.py
datapools/common/counter_cache.py
datapools/common/http.py
datapools/common/logger.py
datapools/common/robots.py
datapools/common/session_manager.py
datapools/common/stoppable.py
datapools/common/types.py
datapools/common/utils.py
datapools/common/queues/__init__.py
datapools/common/queues/channel.py
datapools/common/queues/rabbitmq.py
datapools/common/queues/types.py
datapools/common/storage/__init__.py
datapools/common/storage/base_storage.py
datapools/common/storage/file_storage.py
datapools/common/storage/metadata_storage.py
datapools/common/storage/s3_storage.py
datapools/common/storage/session_file_storage.py
datapools/common/tasks_db/__init__.py
datapools/common/tasks_db/redis.py.bak
datapools/common/tasks_db/tasks_db.py
datapools/producer/__init__.py
datapools/producer/base_producer.py
datapools/scheduler/__init__.py
datapools/scheduler/scheduler.py
datapools/worker/__init__.py
datapools/worker/types.py
datapools/worker/utils.py
datapools/worker/worker.py
datapools/worker/examples/plugins/sample_plugin/__init__.py
datapools/worker/examples/plugins/sample_plugin/sample.py
datapools/worker/plugins/__init__.py
datapools/worker/plugins/base_plugin.py
datapools/worker/plugins/dataphoenix_info/__init__.py
datapools/worker/plugins/dataphoenix_info/dataphoenix_info.py
datapools/worker/plugins/default/__init__.py
datapools/worker/plugins/default/default.py
datapools/worker/plugins/deutsche_welle/__init__.py
datapools/worker/plugins/deutsche_welle/deutsche_welle.py
datapools/worker/plugins/freesound_org/__init__.py
datapools/worker/plugins/freesound_org/freesound_org.py
datapools/worker/plugins/ftp/__init__.py
datapools/worker/plugins/ftp/ftp.py
datapools/worker/plugins/google_drive/__init__.py
datapools/worker/plugins/google_drive/google_drive.py
datapools/worker/plugins/imageshack/__init__.py
datapools-2.0.239.dist-info/LICENSE
datapools-2.0.239.dist-info/METADATA
datapools-2.0.239.dist-info/WHEEL
datapools-2.0.239.dist-info/entry_points.txt
datapools-2.0.239.dist-info/top_level.txt
datapools-2.0.239.dist-info/RECORD
