Metadata-Version: 2.1
Name: datapools
Version: 2.0.239
Summary: Awesome datapools created by openlicenseai
Home-page: https://github.com/openlicenseai/datapools/
Author: openlicenseai
License-File: LICENSE
Requires-Dist: pydantic==2.6.1
Requires-Dist: pydantic-settings==2.2.1
Requires-Dist: email-validator
Requires-Dist: websockets
Requires-Dist: pytube
Requires-Dist: click==8.1.7
Requires-Dist: redis
Requires-Dist: types-redis
Requires-Dist: html2text
Requires-Dist: aiohttp
Requires-Dist: boto3
Requires-Dist: filetype
Requires-Dist: google-api-python-client
Requires-Dist: google-auth-httplib2
Requires-Dist: azure-identity
Requires-Dist: msgraph-sdk
Requires-Dist: aioftp
Requires-Dist: aio-pika
Requires-Dist: dnspython
Requires-Dist: pillow
Requires-Dist: mutagen
Requires-Dist: memory-profiler
Requires-Dist: types-python-dateutil
Requires-Dist: pytest-playwright
Requires-Dist: bs4
Requires-Dist: python-magic
Requires-Dist: cachetools
Requires-Dist: types-cachetools
Requires-Dist: asyncache
Provides-Extra: test
Requires-Dist: pytest; extra == "test"
Requires-Dist: coverage; extra == "test"
Requires-Dist: flake8; extra == "test"
Requires-Dist: black; extra == "test"
Requires-Dist: isort; extra == "test"
Requires-Dist: pytest-cov; extra == "test"
Requires-Dist: mypy; extra == "test"
Requires-Dist: gitchangelog; extra == "test"
Requires-Dist: mkdocs; extra == "test"
Requires-Dist: mkdocs-material; extra == "test"
Requires-Dist: memory-profiler; extra == "test"
Requires-Dist: fastapi; extra == "test"
Requires-Dist: uvicorn; extra == "test"
